LICENSE
README.md
pyproject.toml
requirements.txt
src/radar/__init__.py
src/radar/chart.py
src/radar/common.py
src/radar/cosmetics.py
src/radar/datashop.py
src/radar/fifobuffer.py
src/radar/lrucache.py
src/radar/nexrad.py
src/radar/overlay.py
src/radar/read.py
src/radar/write.py
src/radar/maps/citiesx020.shp.json
src/radar/maps/gz_2010_us_050_00_500k.stq.json
src/radar/maps/intrstat.stq.json
src/radar/maps/states-10m.stq.json
src/radar/product/__init__.py
src/radar/product/client.py
src/radar/product/const.py
src/radar/product/redis-bridge.py
src/radar/product/server.py
src/radar/product/share.py
src/radar_data.egg-info/PKG-INFO
src/radar_data.egg-info/SOURCES.txt
src/radar_data.egg-info/dependency_links.txt
src/radar_data.egg-info/entry_points.txt
src/radar_data.egg-info/requires.txt
src/radar_data.egg-info/top_level.txt
tests/test_read.py