Metadata-Version: 2.4
Name: radar-data
Version: 1.5
Summary: Radar Data
Author-email: Boonleng Cheong <boonleng@ou.edu>
Project-URL: Repository, https://github.com/ouradar/radar-data
Keywords: radar,data,weather
Classifier: Development Status :: 5 - Production/Stable
Classifier: Intended Audience :: Developers
Classifier: Intended Audience :: Education
Classifier: Intended Audience :: Science/Research
Classifier: Operating System :: OS Independent
Classifier: Programming Language :: Python :: 3
Classifier: Programming Language :: Python :: 3.8
Classifier: Programming Language :: Python :: 3.9
Classifier: Programming Language :: Python :: 3.10
Classifier: Programming Language :: Python :: 3.11
Classifier: Programming Language :: Python :: 3.12
Classifier: Topic :: Scientific/Engineering
Classifier: Topic :: Software Development :: Libraries
Classifier: Topic :: Software Development :: Libraries :: Python Modules
Requires-Python: >=3.8
License-File: LICENSE
Requires-Dist: blib-py
Requires-Dist: multiprocess
Requires-Dist: netCDF4
Requires-Dist: numpy
Requires-Dist: pyyaml
Requires-Dist: setproctitle
Dynamic: license-file
